cattr/__init__.py
cattr/converters.py
cattr/disambiguators.py
cattr/dispatch.py
cattr/errors.py
cattr/gen.py
cattr/py.typed
cattr/preconf/__init__.py
cattr/preconf/bson.py
cattr/preconf/json.py
cattr/preconf/msgpack.py
cattr/preconf/orjson.py
cattr/preconf/pyyaml.py
cattr/preconf/tomlkit.py
cattr/preconf/ujson.py
cattrs/__init__.py
cattrs/_compat.py
cattrs/_generics.py
cattrs/converters.py
cattrs/disambiguators.py
cattrs/dispatch.py
cattrs/errors.py
cattrs/fns.py
cattrs/py.typed
cattrs/v.py
cattrs/gen/__init__.py
cattrs/gen/_consts.py
cattrs/gen/_generics.py
cattrs/gen/_lc.py
cattrs/gen/_shared.py
cattrs/gen/typeddicts.py
cattrs/preconf/__init__.py
cattrs/preconf/bson.py
cattrs/preconf/cbor2.py
cattrs/preconf/json.py
cattrs/preconf/msgpack.py
cattrs/preconf/orjson.py
cattrs/preconf/pyyaml.py
cattrs/preconf/tomlkit.py
cattrs/preconf/ujson.py
cattrs/strategies/__init__.py
cattrs/strategies/_class_methods.py
cattrs/strategies/_subclasses.py
cattrs/strategies/_unions.py
cattrs-23.2.0.dist-info/METADATA
cattrs-23.2.0.dist-info/WHEEL
cattrs-23.2.0.dist-info/licenses/LICENSE
cattrs-23.2.0.dist-info/RECORD
