Metadata-Version: 2.1
Name: cattrs
Version: 23.2.0
Summary: Composable complex class support for attrs and dataclasses.
Project-URL: Homepage, https://catt.rs
Project-URL: Changelog, https://catt.rs/en/latest/history.html
Project-URL: Bug Tracker, https://github.com/python-attrs/cattrs/issues
Project-URL: Repository, https://github.com/python-attrs/cattrs
Project-URL: Documentation, https://catt.rs/en/stable/
Author-email: Tin Tvrtkovic <tinchester@gmail.com>
License: MIT
License-File: LICENSE
Keywords: attrs,dataclasses,serialization
Classifier: Development Status :: 5 - Production/Stable
Classifier: Intended Audience :: Developers
Classifier: License :: OSI Approved :: MIT License
Classifier: Programming Language :: Python :: 3.8
Classifier: Programming Language :: Python :: 3.9
Classifier: Programming Language :: Python :: 3.10
Classifier: Programming Language :: Python :: 3.11
Classifier: Programming Language :: Python :: 3.12
Classifier: Programming Language :: Python :: Implementation :: CPython
Classifier: Programming Language :: Python :: Implementation :: PyPy
Classifier: Typing :: Typed
Requires-Python: >=3.8
Requires-Dist: attrs>=23.1.0
Requires-Dist: exceptiongroup>=1.1.1; python_version < '3.11'
Requires-Dist: typing-extensions!=4.6.3,>=4.1.0; python_version < '3.11'
Provides-Extra: bson
Requires-Dist: pymongo>=4.4.0; extra == 'bson'
Provides-Extra: cbor2
Requires-Dist: cbor2>=5.4.6; extra == 'cbor2'
Provides-Extra: msgpack
Requires-Dist: msgpack>=1.0.5; extra == 'msgpack'
Provides-Extra: orjson
Requires-Dist: orjson>=3.9.2; implementation_name == 'cpython' and extra == 'orjson'
Provides-Extra: pyyaml
Requires-Dist: pyyaml>=6.0; extra == 'pyyaml'
Provides-Extra: tomlkit
Requires-Dist: tomlkit>=0.11.8; extra == 'tomlkit'
Provides-Extra: ujson
Requires-Dist: ujson>=5.7.0; extra == 'ujson'
